mfio/__init__.py
mfio/iolib/__init__.py
mfio/iolib/base.py
mfio/iolib/csv.py
mfio/iolib/excel.py
mfio/iolib/img.py
mfio/iolib/json.py
mfio/iolib/txt.py
mfio/iolib/xml.py
mfio/iolib/yaml.py
mfio/scanlib/__init__.py
mfio/scanlib/scan.py
mfio/utils/__init__.py
mfio/utils/download.py
mfio/utils/general.py
mfio/utils/log.py
mfio/utils/print_table.py
mfio-1.3.8.dist-info/METADATA
mfio-1.3.8.dist-info/WHEEL
mfio-1.3.8.dist-info/top_level.txt
mfio-1.3.8.dist-info/RECORD
