Metadata-Version: 2.1
Name: mfio
Version: 1.3.8
Summary: 自用文件读写检索匹配工具
Home-page: https://github.com/MrRabbit2MissCat/mmfio
Author: yunhgu
Author-email: 1508777473@qq.com
License: MIT
Requires-Python: >=3.7
Requires-Dist: loguru
Requires-Dist: xlrd ==1.2.0
Requires-Dist: xlwt
Requires-Dist: numpy
Requires-Dist: opencv-python
Requires-Dist: xmltodict
Requires-Dist: pyyaml
Requires-Dist: requests
Requires-Dist: openpyxl
Requires-Dist: rich
